[
    {
        "id": "2850566993663190494",
        "display_url": "https://instagram.fkiv1-1.fna.fbcdn.net/v/t51.2885-15/284991991_137264432233693_6403576996604679439_n.jpg?stp=dst-jpg_e35_p1080x1080&_nc_ht=instagram.fkiv1-1.fna.fbcdn.net&_nc_cat=101&_nc_ohc=pgQ44SEdXYMAX8ApDb8&edm=APU89FABAAAA&ccb=7-5&ig_cache_key=Mjg1MDU2Njk5MzY2MzE5MDQ5NA%3D%3D.2-ccb7-5&oh=00_AT9OzLNbZ12cZ2sO-69XFDVEfHVjklrRuLz5OyTVpOvFww&oe=62B6519F&_nc_sid=86f79a",
        "shortcode": "CePP5Ppv2Xe",
        "is_video": false,
        "totals": {
            "comments": 30066,
            "likes": 998550,
            "views": 0
        }
    },
    {
        "id": "2838989418179387453",
        "display_url": "https://instagram.fkiv1-1.fna.fbcdn.net/v/t51.2885-15/280720140_760829651749239_4464084748533504717_n.jpg?stp=dst-jpg_e35_p1080x1080&_nc_ht=instagram.fkiv1-1.fna.fbcdn.net&_nc_cat=103&_nc_ohc=xbgyds957YwAX8LAMKF&edm=APU89FABAAAA&ccb=7-5&ig_cache_key=MjgzODk4OTQxODE3OTM4NzQ1Mw%3D%3D.2-ccb7-5&oh=00_AT9DHI42_enKhDLtqVjqJVEuBS3tpME6faXVztqWzO5Jgg&oe=62B57BEA&_nc_sid=86f79a",
        "shortcode": "CdmHdWPrOA9",
        "is_video": false,
        "totals": {
            "comments": 40802,
            "likes": 1013643,
            "views": 0
        }
    },
    {
        "id": "2836799256914827391",
        "display_url": "https://instagram.fkiv1-1.fna.fbcdn.net/v/t51.2885-15/280437400_777190033232329_8967137255746414448_n.jpg?stp=dst-jpg_e15&_nc_ht=instagram.fkiv1-1.fna.fbcdn.net&_nc_cat=101&_nc_ohc=ADyuXy2XlIQAX-H8gNt&edm=APU89FABAAAA&ccb=7-5&oh=00_AT-qgFAOcgQu6NB7DlMYzNi1sWorv3HaoW8F5Is1dcl6uw&oe=62B12285&_nc_sid=86f79a",
        "shortcode": "CdeVeTngBh_",
        "is_video": true,
        "totals": {
            "comments": 10413,
            "likes": 221170,
            "views": 2507476
        }
    },
    {
        "id": "2834624895722421899",
        "display_url": "https://instagram.fkiv1-1.fna.fbcdn.net/v/t51.2885-15/280437400_494352872472127_7080081156017527406_n.jpg?stp=dst-jpg_e15&_nc_ht=instagram.fkiv1-1.fna.fbcdn.net&_nc_cat=107&_nc_ohc=FZwPkodxbp0AX9gbcpM&edm=APU89FABAAAA&ccb=7-5&oh=00_AT_hh2ks7JFADg2SGrbdv_T-Y3Fs-HbbRaS133W1UZokjA&oe=62B0A80B&_nc_sid=86f79a",
        "shortcode": "CdWnFL9A36L",
        "is_video": true,
        "totals": {
            "comments": 10966,
            "likes": 249459,
            "views": 1625018
        }
    },
    {
        "id": "2831757241286340857",
        "display_url": "https://instagram.fkiv1-1.fna.fbcdn.net/v/t51.2885-15/279827929_528962952275570_8160218456682024173_n.jpg?stp=dst-jpg_e15&_nc_ht=instagram.fkiv1-1.fna.fbcdn.net&_nc_cat=102&_nc_ohc=EgN3G-s9CPwAX9KajtB&edm=APU89FABAAAA&ccb=7-5&oh=00_AT8GkCJ15TGGsU9wID36TC7WBOrNECRdBEJBIXGFzKYvQg&oe=62B0B657&_nc_sid=86f79a",
        "shortcode": "CdMbDUpAzD5",
        "is_video": true,
        "totals": {
            "comments": 11388,
            "likes": 269660,
            "views": 1804176
        }
    },
    {
        "id": "2830810254390854680",
        "display_url": "https://instagram.fkiv1-1.fna.fbcdn.net/v/t51.2885-15/280013784_499132744993177_46241258477748386_n.jpg?stp=dst-jpg_e15&_nc_ht=instagram.fkiv1-1.fna.fbcdn.net&_nc_cat=101&_nc_ohc=qwj3xIyiGzEAX_OBKWO&edm=APU89FABAAAA&ccb=7-5&oh=00_AT8gvLrJ_pQmm3RDJiefjxTTkscy0xU5pwqnD9wCDW9Kww&oe=62B10B24&_nc_sid=86f79a",
        "shortcode": "CdJDu2XgAQY",
        "is_video": true,
        "totals": {
            "comments": 12435,
            "likes": 244566,
            "views": 2170835
        }
    },
    {
        "id": "2830299975419475975",
        "display_url": "https://instagram.fkiv1-1.fna.fbcdn.net/v/t51.2885-15/279686383_1681871475498299_5013020990443037863_n.jpg?stp=dst-jpg_e35_p1080x1080&_nc_ht=instagram.fkiv1-1.fna.fbcdn.net&_nc_cat=111&_nc_ohc=aYzlYjNRODoAX9WTKrX&edm=APU89FABAAAA&ccb=7-5&ig_cache_key=MjgzMDI5OTk3NTQxOTQ3NTk3NQ%3D%3D.2-ccb7-5&oh=00_AT8_nNAFAs4FSPl-OUSU4J0SzVXQqiBMTi_EFJXfd_0d-w&oe=62B625AA&_nc_sid=86f79a",
        "shortcode": "CdHPtUCrLgH",
        "is_video": false,
        "totals": {
            "comments": 12158,
            "likes": 576614,
            "views": 0
        }
    },
    {
        "id": "2829619960201734700",
        "display_url": "https://instagram.fkiv1-1.fna.fbcdn.net/v/t51.2885-15/279709748_949861202354655_6286609658018537601_n.jpg?stp=dst-jpg_e35_s1080x1080&_nc_ht=instagram.fkiv1-1.fna.fbcdn.net&_nc_cat=103&_nc_ohc=iD03sZc7L68AX-Npstl&edm=APU89FABAAAA&ccb=7-5&ig_cache_key=MjgyOTYxOTk2MDIwMTczNDcwMA%3D%3D.2-ccb7-5&oh=00_AT-_QM2yHjb8q0lfEBUAqMJxPy6P36GatDgbFcKeW-iWFg&oe=62B5643C&_nc_sid=86f79a",
        "shortcode": "CdE1FyhLeos",
        "is_video": false,
        "totals": {
            "comments": 12959,
            "likes": 310838,
            "views": 0
        }
    },
    {
        "id": "2828246405635508506",
        "display_url": "https://instagram.fkiv1-1.fna.fbcdn.net/v/t51.2885-15/279460377_1042133463367919_6776406625406110216_n.jpg?stp=dst-jpg_e35_s1080x1080&_nc_ht=instagram.fkiv1-1.fna.fbcdn.net&_nc_cat=111&_nc_ohc=qpr4DuSuiTkAX8Ksa1X&edm=APU89FABAAAA&ccb=7-5&ig_cache_key=MjgyODI0NjQwNTYzNTUwODUwNg%3D%3D.2-ccb7-5&oh=00_AT_RNpUH3GbddIRnpxxjm-f6laRtI9pwvO1soTwFngWBmg&oe=62B571C8&_nc_sid=86f79a",
        "shortcode": "Cc_8x8JLgka",
        "is_video": false,
        "totals": {
            "comments": 13961,
            "likes": 561135,
            "views": 0
        }
    },
    {
        "id": "2826517463044055268",
        "display_url": "https://instagram.fkiv1-1.fna.fbcdn.net/v/t51.2885-15/279237409_3171395386460207_8063043796437138214_n.jpg?se=7&stp=dst-jpg_e35&_nc_ht=instagram.fkiv1-1.fna.fbcdn.net&_nc_cat=111&_nc_ohc=oew8vz6dWyEAX_3iGZZ&edm=APU89FABAAAA&ccb=7-5&ig_cache_key=MjgyNjUxNzQ2MzA0NDA1NTI2OA%3D%3D.2-ccb7-5&oh=00_AT_sU-vuLE5gmfDscdbmKcyaRZL65ODoTC5lWyAI-fyz5w&oe=62B59D5F&_nc_sid=86f79a",
        "shortcode": "Cc5zqg4LeDk",
        "is_video": false,
        "totals": {
            "comments": 18820,
            "likes": 365770,
            "views": 0
        }
    },
    {
        "id": "2826386826368060988",
        "display_url": "https://instagram.fkiv1-1.fna.fbcdn.net/v/t51.2885-15/279341527_3159513667710693_8195282166818478361_n.jpg?stp=dst-jpg_e15&_nc_ht=instagram.fkiv1-1.fna.fbcdn.net&_nc_cat=109&_nc_ohc=zyaaMV8h8DEAX-oIdWZ&edm=APU89FABAAAA&ccb=7-5&oh=00_AT9WEbwQhpjCnmd9FyZ2cOdkl4Ndf6T7TTiQgh8vGuA8jQ&oe=62B0ED0F&_nc_sid=86f79a",
        "shortcode": "Cc5V9f_gw48",
        "is_video": true,
        "totals": {
            "comments": 7146,
            "likes": 319743,
            "views": 1944048
        }
    },
    {
        "id": "2825752826129518341",
        "display_url": "https://instagram.fkiv1-1.fna.fbcdn.net/v/t51.2885-15/279205286_1112537646262975_8455429319306277079_n.jpg?stp=dst-jpg_e15&_nc_ht=instagram.fkiv1-1.fna.fbcdn.net&_nc_cat=107&_nc_ohc=cbP9A_1TfAQAX_ZHG9j&edm=APU89FABAAAA&ccb=7-5&oh=00_AT9evVEqV-_xKDaAvtWZhCYW05oUkUstbJ6ySCtTFgnn-Q&oe=62B12843&_nc_sid=86f79a",
        "shortcode": "Cc3FzlQgY8F",
        "is_video": true,
        "totals": {
            "comments": 7182,
            "likes": 335684,
            "views": 1686973
        }
    },
    {
        "id": "2825280461904794170",
        "display_url": "https://instagram.fkiv1-1.fna.fbcdn.net/v/t51.2885-15/279157394_307027128219450_401558721025830277_n.jpg?stp=dst-jpg_e35_s1080x1080&_nc_ht=instagram.fkiv1-1.fna.fbcdn.net&_nc_cat=106&_nc_ohc=a7_UkBDO86wAX9kfFcC&edm=APU89FABAAAA&ccb=7-5&ig_cache_key=MjgyNTI4MDQ2MTkwNDc5NDE3MA%3D%3D.2-ccb7-5&oh=00_AT9ehNqNjPwDMvHjTXfnHTue080fQCT2vQwiqft7wQXdJA&oe=62B4AB59&_nc_sid=86f79a",
        "shortcode": "Cc1aZxyr9I6",
        "is_video": false,
        "totals": {
            "comments": 19208,
            "likes": 858408,
            "views": 0
        }
    },
    {
        "id": "2824474809683737326",
        "display_url": "https://instagram.fkiv1-1.fna.fbcdn.net/v/t51.2885-15/279117158_382449370448508_1096561370312889566_n.jpg?stp=dst-jpg_e35_s1080x1080&_nc_ht=instagram.fkiv1-1.fna.fbcdn.net&_nc_cat=100&_nc_ohc=nm_h4QfD8tUAX_HFt6V&edm=APU89FABAAAA&ccb=7-5&ig_cache_key=MjgyNDQ3NDgwOTY4MzczNzMyNg%3D%3D.2-ccb7-5&oh=00_AT-YlVaX3Rbs_EL799lSFz8F5ff0DLPn0fexdcCtm2IFHw&oe=62B62E9C&_nc_sid=86f79a",
        "shortcode": "CcyjN_sPPru",
        "is_video": false,
        "totals": {
            "comments": 11449,
            "likes": 382185,
            "views": 0
        }
    },
    {
        "id": "2820640341725341063",
        "display_url": "https://instagram.fkiv1-1.fna.fbcdn.net/v/t51.2885-15/278705741_690043305577879_7071898896794853713_n.jpg?se=7&stp=dst-jpg_e35&_nc_ht=instagram.fkiv1-1.fna.fbcdn.net&_nc_cat=107&_nc_ohc=m9jz_6j0z8sAX8XfvWJ&edm=APU89FABAAAA&ccb=7-5&ig_cache_key=MjgyMDY0MDM0MTcyNTM0MTA2Mw%3D%3D.2-ccb7-5&oh=00_AT9FBwqnbVeYTRb37LTI3srmgVWXhIeR_sj4EeCDNp7RNA&oe=62B613B9&_nc_sid=86f79a",
        "shortcode": "Cck7XJHrOWH",
        "is_video": false,
        "totals": {
            "comments": 51325,
            "likes": 631183,
            "views": 0
        }
    },
    {
        "id": "2819825606436202965",
        "display_url": "https://instagram.fkiv1-1.fna.fbcdn.net/v/t51.2885-15/278716172_147784927747098_5538400914371136902_n.jpg?stp=dst-jpg_e35_s1080x1080&_nc_ht=instagram.fkiv1-1.fna.fbcdn.net&_nc_cat=106&_nc_ohc=71FoWpU2dk0AX9ZBrYk&edm=APU89FABAAAA&ccb=7-5&ig_cache_key=MjgxOTgyNTYwNjQzNjIwMjk2NQ%3D%3D.2-ccb7-5&oh=00_AT80coVOOewlWGO93-dDAsQby8H-LVt_huX1LI9tYo5r5Q&oe=62B4D1C6&_nc_sid=86f79a",
        "shortcode": "CciCHLwLinV",
        "is_video": false,
        "totals": {
            "comments": 10761,
            "likes": 347601,
            "views": 0
        }
    },
    {
        "id": "2819226355419289660",
        "display_url": "https://instagram.fkiv1-1.fna.fbcdn.net/v/t51.2885-15/278811203_2131397147033535_6949089487379067152_n.jpg?stp=dst-jpg_e35_p1080x1080&_nc_ht=instagram.fkiv1-1.fna.fbcdn.net&_nc_cat=103&_nc_ohc=Y5iYvimzsGkAX9rZL4p&edm=APU89FABAAAA&ccb=7-5&ig_cache_key=MjgxOTIyNjM1NTQxOTI4OTY2MA%3D%3D.2-ccb7-5&oh=00_AT9HfG52hCw-Pg9kXYkiHwBn_ao1nXJnLbxbumndbC7s4g&oe=62B65F7C&_nc_sid=86f79a",
        "shortcode": "Ccf527wL5g8",
        "is_video": false,
        "totals": {
            "comments": 10901,
            "likes": 276494,
            "views": 0
        }
    },
    {
        "id": "2818528239671213313",
        "display_url": "https://instagram.fkiv1-1.fna.fbcdn.net/v/t51.2885-15/278567464_502591374690608_8011638129893860434_n.jpg?stp=dst-jpg_e15&_nc_ht=instagram.fkiv1-1.fna.fbcdn.net&_nc_cat=108&_nc_ohc=aUQysOxb0rAAX_4eQNR&edm=APU89FABAAAA&ccb=7-5&oh=00_AT-Stpnw0TAl1eQtHwlP09yLjnRS1jKULp492ahXPv9BhQ&oe=62B0D30D&_nc_sid=86f79a",
        "shortcode": "CcdbIAzAn0B",
        "is_video": true,
        "totals": {
            "comments": 16140,
            "likes": 510878,
            "views": 3797927
        }
    },
    {
        "id": "2818506488021898926",
        "display_url": "https://instagram.fkiv1-1.fna.fbcdn.net/v/t51.2885-15/278587300_685903726046796_4161110314851393321_n.jpg?se=7&stp=dst-jpg_e35&_nc_ht=instagram.fkiv1-1.fna.fbcdn.net&_nc_cat=100&_nc_ohc=Dq70djiaNoMAX88P5uv&edm=APU89FABAAAA&ccb=7-5&ig_cache_key=MjgxODUwNjQ4ODAyMTg5ODkyNg%3D%3D.2-ccb7-5&oh=00_AT8efDnXzgygfeJZH5CLA_hy2WkTS91nujlILuqSn8gFoA&oe=62B6059A&_nc_sid=86f79a",
        "shortcode": "CcdWLe_rdau",
        "is_video": false,
        "totals": {
            "comments": 47376,
            "likes": 573376,
            "views": 0
        }
    },
    {
        "id": "2815058353196036404",
        "display_url": "https://instagram.fkiv1-1.fna.fbcdn.net/v/t51.2885-15/278177002_341649878026096_1164426497083734569_n.jpg?se=7&stp=dst-jpg_e35&_nc_ht=instagram.fkiv1-1.fna.fbcdn.net&_nc_cat=104&_nc_ohc=ayvW7ymV5iIAX867TgG&edm=APU89FABAAAA&ccb=7-5&ig_cache_key=MjgxNTA1ODM1MzE5NjAzNjQwNA%3D%3D.2-ccb7-5&oh=00_AT9xgfWYS2dp0tVaN666afctcWK_0xPUxSkeQADnHsy6zg&oe=62B4CD44&_nc_sid=86f79a",
        "shortcode": "CcRGKhMPvE0",
        "is_video": false,
        "totals": {
            "comments": 16545,
            "likes": 385647,
            "views": 0
        }
    }
]