[
    {
        "id": "2867281658773514668",
        "display_url": "https://scontent-hel3-1.cdninstagram.com/v/t51.2885-15/289516429_174715201670333_8961522627291237634_n.jpg?stp=dst-jpg_e35_p1080x1080&_nc_ht=scontent-hel3-1.cdninstagram.com&_nc_cat=1&_nc_ohc=oMeem7gbX7MAX81c3MD&edm=APU89FABAAAA&ccb=7-5&ig_cache_key=Mjg2NzI4MTY1MzExMTM5OTgwMQ%3D%3D.2-ccb7-5&oh=00_AT-wligrKryRNzBczuiZENSZzGToY64xYpaVDaeugpo8kQ&oe=62BC39CB&_nc_sid=86f79a",
        "shortcode": "CfKoXomMCms",
        "is_video": false,
        "totals": {
            "comments": 410,
            "likes": 9567,
            "views": 0
        }
    },
    {
        "id": "2866685190786424175",
        "display_url": "https://scontent-hel3-1.cdninstagram.com/v/t51.2885-15/289540195_1835229550147217_5924667638867110403_n.jpg?stp=dst-jpg_e35_p1080x1080&_nc_ht=scontent-hel3-1.cdninstagram.com&_nc_cat=105&_nc_ohc=9o5OmF-r4wAAX_lMjh_&edm=APU89FABAAAA&ccb=7-5&ig_cache_key=Mjg2NjY4NTE4NjU2Njk4MzU4NA%3D%3D.2-ccb7-5&oh=00_AT8W_qJNE4EaqyBn4UtZ1ISydE_njBvcOgVp4fplaBZWHw&oe=62BBB5DC&_nc_sid=86f79a",
        "shortcode": "CfIgv4fsp1v",
        "is_video": false,
        "totals": {
            "comments": 667,
            "likes": 35406,
            "views": 0
        }
    },
    {
        "id": "2864391738892265801",
        "display_url": "https://scontent-hel3-1.cdninstagram.com/v/t51.2885-15/289051734_175451994864484_101723005686119334_n.jpg?stp=dst-jpg_e15&_nc_ht=scontent-hel3-1.cdninstagram.com&_nc_cat=104&_nc_ohc=iwD6nXP-H50AX_b62Fz&edm=APU89FABAAAA&ccb=7-5&oh=00_AT-1bkAARGXmnbe_GO-G_aVNntLHPJEvq2X0SWmG8QrGDw&oe=62B75178&_nc_sid=86f79a",
        "shortcode": "CfAXRw-PKlJ",
        "is_video": true,
        "totals": {
            "comments": 503,
            "likes": 11573,
            "views": 76001
        }
    },
    {
        "id": "2862255552785951599",
        "display_url": "https://scontent-hel3-1.cdninstagram.com/v/t51.2885-15/288256420_153718570517922_4619259817790501876_n.jpg?stp=dst-jpg_e35_p1080x1080&_nc_ht=scontent-hel3-1.cdninstagram.com&_nc_cat=106&_nc_ohc=mFWBs_RMEywAX-MkuXF&edm=APU89FABAAAA&ccb=7-5&ig_cache_key=Mjg2MjI1NTU0NzQwMDQ2MDAxOA%3D%3D.2-ccb7-5&oh=00_AT8EmXkqC1bKJ-kXtRMvH6NURHpYob-hxB3T9iCsZ79xzA&oe=62BBBE60&_nc_sid=86f79a",
        "shortcode": "Ce4xkKoMitv",
        "is_video": false,
        "totals": {
            "comments": 1313,
            "likes": 119594,
            "views": 0
        }
    },
    {
        "id": "2861290474238372795",
        "display_url": "https://scontent-hel3-1.cdninstagram.com/v/t51.2885-15/288042335_552060376362345_2467731358525081075_n.jpg?stp=dst-jpg_e35_p1080x1080&_nc_ht=scontent-hel3-1.cdninstagram.com&_nc_cat=109&_nc_ohc=lJNd6wQIcRwAX8OOcI6&edm=APU89FABAAAA&ccb=7-5&ig_cache_key=Mjg2MTI5MDQ2OTc3NTU0NTY0NA%3D%3D.2-ccb7-5&oh=00_AT88c2qmp2-f2UgEt1H9gQOLZwZkwu0SrNZ7Ln6inavf5w&oe=62BC5463&_nc_sid=86f79a",
        "shortcode": "Ce1WIbML-u7",
        "is_video": false,
        "totals": {
            "comments": 1096,
            "likes": 65608,
            "views": 0
        }
    },
    {
        "id": "2860472479388339998",
        "display_url": "https://scontent-hel3-1.cdninstagram.com/v/t51.2885-15/288079881_879749216170052_4059551854891734062_n.jpg?stp=dst-jpg_e35_p1080x1080&_nc_ht=scontent-hel3-1.cdninstagram.com&_nc_cat=108&_nc_ohc=LOkCI3BHYS0AX-WHmfh&edm=APU89FABAAAA&ccb=7-5&ig_cache_key=Mjg2MDQ3MjQ3OTM4ODMzOTk5OA%3D%3D.2-ccb7-5&oh=00_AT8n1nd4YhzXyZ3KWrsyZFZVnze8CogQu_ReECMUl5orXA&oe=62BB590C&_nc_sid=86f79a",
        "shortcode": "CeycJCHuQ8e",
        "is_video": false,
        "totals": {
            "comments": 603,
            "likes": 21273,
            "views": 0
        }
    },
    {
        "id": "2859194634064022345",
        "display_url": "https://scontent-hel3-1.cdninstagram.com/v/t51.2885-15/287135563_2146235145551343_387458724051499189_n.jpg?stp=dst-jpg_e35_p1080x1080&_nc_ht=scontent-hel3-1.cdninstagram.com&_nc_cat=103&_nc_ohc=88h5QmQ-RYkAX-JM6aD&edm=APU89FABAAAA&ccb=7-5&ig_cache_key=Mjg1OTE5NDYyOTk1MzY2NzYzNw%3D%3D.2-ccb7-5&oh=00_AT8K9AY3k1faTUqwV2KKHLHPZIr6tLW4x2dOP1aOxZPO3A&oe=62BCF6D2&_nc_sid=86f79a",
        "shortcode": "Cet5l77FstJ",
        "is_video": false,
        "totals": {
            "comments": 1090,
            "likes": 67625,
            "views": 0
        }
    },
    {
        "id": "2858368662101711544",
        "display_url": "https://scontent-hel3-1.cdninstagram.com/v/t51.2885-15/287583417_491330692741540_2312081669057677080_n.jpg?stp=dst-jpg_e15&_nc_ht=scontent-hel3-1.cdninstagram.com&_nc_cat=104&_nc_ohc=bTnloX8839QAX_SlemF&edm=APU89FABAAAA&ccb=7-5&oh=00_AT9osuP0Glr2zF2xG46Pv8tEiReiuWkJcBUG3TWB4pLnJQ&oe=62B77062&_nc_sid=86f79a",
        "shortcode": "Ceq9ydlrlq4",
        "is_video": true,
        "totals": {
            "comments": 601,
            "likes": 35952,
            "views": 229898
        }
    },
    {
        "id": "2857834370435023276",
        "display_url": "https://scontent-hel3-1.cdninstagram.com/v/t51.2885-15/287513705_568359348034560_5888397462122186388_n.jpg?se=7&stp=dst-jpg_e35&_nc_ht=scontent-hel3-1.cdninstagram.com&_nc_cat=100&_nc_ohc=Oa-g5rg6pgMAX8oCoCA&edm=APU89FABAAAA&ccb=7-5&ig_cache_key=Mjg1NzgzNDM3MDQzNTAyMzI3Ng%3D%3D.2-ccb7-5&oh=00_AT_y0jjYu1u1xr1JThVwnMElhLjZkS17iHRt4DXtfQ2Abw&oe=62BC2030&_nc_sid=86f79a",
        "shortcode": "CepETfsroGs",
        "is_video": false,
        "totals": {
            "comments": 2828,
            "likes": 70379,
            "views": 0
        }
    },
    {
        "id": "2856973328878744248",
        "display_url": "https://scontent-hel3-1.cdninstagram.com/v/t51.2885-15/286456966_5281852738544685_6477911213820763301_n.jpg?stp=dst-jpg_e15&_nc_ht=scontent-hel3-1.cdninstagram.com&_nc_cat=109&_nc_ohc=UvjfaaHzw9kAX8PdSxY&edm=APU89FABAAAA&ccb=7-5&oh=00_AT_GaghwZE8sbxeUeUCAeOchNKr2lDtVssBHfx7kwunuyw&oe=62B74FBD&_nc_sid=86f79a",
        "shortcode": "CemAhsQlTK4",
        "is_video": true,
        "totals": {
            "comments": 1005,
            "likes": 52729,
            "views": 348258
        }
    },
    {
        "id": "2855809011145221805",
        "display_url": "https://instagram.fkiv1-1.fna.fbcdn.net/v/t51.2885-15/286513658_1053314982237024_2216972641413709231_n.jpg?stp=dst-jpg_e35&_nc_ht=instagram.fkiv1-1.fna.fbcdn.net&_nc_cat=100&_nc_ohc=OQ5fHaEvn50AX9v-khs&edm=APU89FABAAAA&ccb=7-5&oh=00_AT997p3zyvOQU4fSJAINFBcJZP0QASRpKwcnC9Z04TcBPg&oe=62B755F8&_nc_sid=86f79a",
        "shortcode": "Ceh3yo3q6at",
        "is_video": true,
        "totals": {
            "comments": 560,
            "likes": 14973,
            "views": 127927
        }
    },
    {
        "id": "2855788772664133135",
        "display_url": "https://instagram.fkiv1-1.fna.fbcdn.net/v/t51.2885-15/286603740_133558765722953_8850510528106635767_n.jpg?stp=dst-jpg_e35_s1080x1080&_nc_ht=instagram.fkiv1-1.fna.fbcdn.net&_nc_cat=105&_nc_ohc=1qYS-zPKEWUAX-zLi3y&edm=APU89FABAAAA&ccb=7-5&ig_cache_key=Mjg1NTc4ODc3MjY2NDEzMzEzNQ%3D%3D.2-ccb7-5&oh=00_AT-4yDRy4VO-sTPxk7ZXBmiTrG57chMQLVEf9Lf_hjBMAA&oe=62BBB6A8&_nc_sid=86f79a",
        "shortcode": "CehzMIUMcYP",
        "is_video": false,
        "totals": {
            "comments": 1521,
            "likes": 114793,
            "views": 0
        }
    },
    {
        "id": "2854196295595074608",
        "display_url": "https://instagram.fkiv1-1.fna.fbcdn.net/v/t51.2885-15/285888417_543928210771770_2066879399869351096_n.jpg?stp=dst-jpg_e35_p1080x1080&_nc_ht=instagram.fkiv1-1.fna.fbcdn.net&_nc_cat=106&_nc_ohc=dKNOoKQSn2MAX98izuG&edm=APU89FABAAAA&ccb=7-5&ig_cache_key=Mjg1NDE5NjI5NTU5NTA3NDYwOA%3D%3D.2-ccb7-5&oh=00_AT_5bmkF8i8TcnwQnbWXtAhBNopAHUJz87_KbYLahvoLOQ&oe=62BC2304&_nc_sid=86f79a",
        "shortcode": "CecJGieLiQw",
        "is_video": false,
        "totals": {
            "comments": 500,
            "likes": 36716,
            "views": 0
        }
    },
    {
        "id": "2852099332338960424",
        "display_url": "https://instagram.fkiv1-1.fna.fbcdn.net/v/t51.2885-15/285470224_398699832271201_1486283404240445343_n.jpg?stp=dst-jpg_e35_p1080x1080&_nc_ht=instagram.fkiv1-1.fna.fbcdn.net&_nc_cat=101&_nc_ohc=uNsl6qA5TokAX-EFrRj&edm=APU89FABAAAA&ccb=7-5&ig_cache_key=Mjg1MjA5OTMyNTYxMTMzNzM1Mg%3D%3D.2-ccb7-5&oh=00_AT8l0bTTJcZVJEwmDIVpx_RcBhVegH-CxcfO7znZboRpAQ&oe=62BB7EF9&_nc_sid=86f79a",
        "shortcode": "CeUsTtQMUgo",
        "is_video": false,
        "totals": {
            "comments": 1825,
            "likes": 93985,
            "views": 0
        }
    },
    {
        "id": "2846237312401635043",
        "display_url": "https://instagram.fkiv1-1.fna.fbcdn.net/v/t51.2885-15/283935627_3143541339234347_6276059295790996957_n.jpg?stp=dst-jpg_e35&_nc_ht=instagram.fkiv1-1.fna.fbcdn.net&_nc_cat=111&_nc_ohc=S4M6ovZoqWgAX_1Xb9f&edm=APU89FABAAAA&ccb=7-5&oh=00_AT-ZaBaVFHAQpsFTpCxn5nQj2KmO97EbSuWy9q-2wz-MVA&oe=62B7971F&_nc_sid=86f79a",
        "shortcode": "Cd_3cFwKXbj",
        "is_video": true,
        "totals": {
            "comments": 612,
            "likes": 20053,
            "views": 276145
        }
    },
    {
        "id": "2838753351140438360",
        "display_url": "https://instagram.fkiv1-1.fna.fbcdn.net/v/t51.2885-15/280778826_1065827937646681_7985682005538231790_n.jpg?stp=dst-jpg_e35_p1080x1080&_nc_ht=instagram.fkiv1-1.fna.fbcdn.net&_nc_cat=101&_nc_ohc=8SA_rCQmWtkAX_or2ig&edm=APU89FABAAAA&ccb=7-5&ig_cache_key=MjgzODc1MzM0NjI1ODIyOTk5Mg%3D%3D.2-ccb7-5&oh=00_AT-EXiWHf_lx8HUFy40KiqogNLCS--ppXgBVrdm7WFGwOw&oe=62BCAF8F&_nc_sid=86f79a",
        "shortcode": "CdlRyHrrPFY",
        "is_video": false,
        "totals": {
            "comments": 4353,
            "likes": 173231,
            "views": 0
        }
    },
    {
        "id": "2833929106427194081",
        "display_url": "https://instagram.fkiv1-1.fna.fbcdn.net/v/t51.2885-15/280172410_748258839510373_6627672404441749675_n.jpg?stp=dst-jpg_e15&_nc_ht=instagram.fkiv1-1.fna.fbcdn.net&_nc_cat=101&_nc_ohc=-VRTgvM_PyoAX_wqFtW&edm=APU89FABAAAA&ccb=7-5&oh=00_AT9CqLyC0YVHpMUMOy0ulLbzHFHQOJE-fr7uW1nZ-po7Hw&oe=62B7C747&_nc_sid=86f79a",
        "shortcode": "CdUI4HrO6rh",
        "is_video": true,
        "totals": {
            "comments": 1050,
            "likes": 38528,
            "views": 342175
        }
    },
    {
        "id": "2833843103412507981",
        "display_url": "https://instagram.fkiv1-1.fna.fbcdn.net/v/t51.2885-15/280115622_341761538054688_2390529408633300962_n.jpg?stp=dst-jpg_e35_p1080x1080&_nc_ht=instagram.fkiv1-1.fna.fbcdn.net&_nc_cat=100&_nc_ohc=xxp_u8uVpbIAX_VoS6-&edm=APU89FABAAAA&ccb=7-5&ig_cache_key=MjgzMzg0MzA5ODYzMDg4MDUwMw%3D%3D.2-ccb7-5&oh=00_AT-YlOq6Ey1hOSb-LUgLELCTnbvhiXsnFLs0PQotku-d0Q&oe=62BB6FEE&_nc_sid=86f79a",
        "shortcode": "CdT1UnIF9VN",
        "is_video": false,
        "totals": {
            "comments": 2240,
            "likes": 323430,
            "views": 0
        }
    },
    {
        "id": "2833025558794702742",
        "display_url": "https://instagram.fkiv1-1.fna.fbcdn.net/v/t51.2885-15/280094894_497785368752931_1272516021671048936_n.jpg?stp=dst-jpg_e15&_nc_ht=instagram.fkiv1-1.fna.fbcdn.net&_nc_cat=103&_nc_ohc=PxfFQh0XkAUAX8uY-hK&edm=APU89FABAAAA&ccb=7-5&oh=00_AT_H5C3Zofm5e2N7qTHQ8-5ep0E_j9GMLDbJ6c3GY8n6oQ&oe=62B75786&_nc_sid=86f79a",
        "shortcode": "CdQ7bxXj4-W",
        "is_video": true,
        "totals": {
            "comments": 3610,
            "likes": 100347,
            "views": 661755
        }
    },
    {
        "id": "2829608325823501970",
        "display_url": "https://instagram.fkiv1-1.fna.fbcdn.net/v/t51.2885-15/279786468_178188291213089_4980847191394826461_n.jpg?se=8&stp=dst-jpg_e35&_nc_ht=instagram.fkiv1-1.fna.fbcdn.net&_nc_cat=105&_nc_ohc=C2cCydyJmAEAX-Rf8IY&edm=APU89FABAAAA&ccb=7-5&ig_cache_key=MjgyOTYwODMyMTc4ODQzMjcxMw%3D%3D.2-ccb7-5&oh=00_AT8Y247g4usXDh8XoIBlfSiqIk1eiJyeSlSX0HpP0pDq6Q&oe=62BC7DD8&_nc_sid=86f79a",
        "shortcode": "CdEycfKMpaS",
        "is_video": false,
        "totals": {
            "comments": 11022,
            "likes": 224405,
            "views": 0
        }
    }
]